MANIFEST.in
README.txt
setup.py
medialog/.DS_Store
medialog/__init__.py
medialog.lxml.egg-info/PKG-INFO
medialog.lxml.egg-info/SOURCES.txt
medialog.lxml.egg-info/dependency_links.txt
medialog.lxml.egg-info/entry_points.txt
medialog.lxml.egg-info/namespace_packages.txt
medialog.lxml.egg-info/not-zip-safe
medialog.lxml.egg-info/requires.txt
medialog.lxml.egg-info/top_level.txt
medialog/lxml/.DS_Store
medialog/lxml/__init__.py
medialog/lxml/behavior.py
medialog/lxml/behaviors.zcml
medialog/lxml/configure.zcml
medialog/lxml/interfaces.py
medialog/lxml/scrape.pt
medialog/lxml/scrape_view.pt
medialog/lxml/views.py
medialog/lxml/profiles/default/metadata.xml
medialog/lxml/profiles/default/registry.xml