Metadata-Version: 1.0
Name: medialog.lxml
Version: 0.4
Summary: A Product to embed/add/migrate content with lxml
Home-page: http://github.com/espenmn/medialog.lxml
Author: Espen Moe-Nilssen
Author-email: espen@medialog.no
License: gpl
Keywords: embed plone lxml migrate csv impoort
Platform: UNKNOWN
Classifier: Environment :: Web Environment
Classifier: Framework :: Plone
Classifier: Framework :: Plone :: 4.1
Classifier: Framework :: Plone :: 4.2
Classifier: Framework :: Plone :: 4.3
Classifier: Framework :: Zope2
Classifier: Framework :: Zope3
Classifier: Intended Audience :: Developers
Classifier: Intended Audience :: End Users/Desktop
Classifier: Operating System :: OS Independent
Classifier: Programming Language :: Python
Classifier: Programming Language :: Python :: 2.6
Classifier: Programming Language :: Python :: 2.7
Classifier: Topic :: Internet
Classifier: Topic :: Software Development :: Libraries :: Python Modules
